appython/__init__.py
appython/protector.py
appython/service/auth_token_provider.py
appython/service/payload_builder.py
appython/service/request_handler.py
appython/service/response_handler.py
appython/utils/codec_helper.py
appython/utils/constants.py
appython/utils/exceptions.py
appython/utils/input_preprocessor.py
appython/utils/output_postprocessor.py
protegrity_developer_python/__init__.py
protegrity_developer_python/scan.py
protegrity_developer_python/securefind.py
protegrity_developer_python/utils/ccn_processing.py
protegrity_developer_python/utils/config.py
protegrity_developer_python/utils/constants.py
protegrity_developer_python/utils/discover.py
protegrity_developer_python/utils/logger.py
protegrity_developer_python/utils/pii_processing.py
protegrity_developer_python/utils/protector.py
protegrity_developer_python/utils/semantic_guardrails.py
protegrity_developer_python-1.1.1.dist-info/licenses/LICENSE
protegrity_developer_python-1.1.1.dist-info/METADATA
protegrity_developer_python-1.1.1.dist-info/WHEEL
protegrity_developer_python-1.1.1.dist-info/top_level.txt
protegrity_developer_python-1.1.1.dist-info/RECORD
