Metadata-Version: 2.4
Name: protegrity-developer-python
Version: 1.1.1
Summary: Python module for integrating Protegrity's Data Discovery and Protection APIs into GenAI and traditional applications.
Home-page: https://www.protegrity.com/developers
Author: Protegrity
Author-email: Protegrity <info@protegrity.com>
License-Expression: MIT
Project-URL: homepage, https://www.protegrity.com/developers
Project-URL: repository, https://github.com/Protegrity-Developer-Edition/protegrity-developer-python
Project-URL: documentation, http://developer.docs.protegrity.com
Requires-Python: >=3.12.11
License-File: LICENSE
Requires-Dist: requests
Dynamic: license-file
